pynxtools_em/__init__.py
pynxtools_em/mkdocs.py
pynxtools_em/reader.py
pynxtools_em/concepts/hfive_concepts.py
pynxtools_em/concepts/mapping_functors_pint.py
pynxtools_em/concepts/nxs_concepts.py
pynxtools_em/configurations/conventions_cfg.py
pynxtools_em/configurations/image_png_protochips_cfg.py
pynxtools_em/configurations/image_tiff_fei_cfg.py
pynxtools_em/configurations/image_tiff_hitachi_cfg.py
pynxtools_em/configurations/image_tiff_jeol_cfg.py
pynxtools_em/configurations/image_tiff_point_electronic_cfg.py
pynxtools_em/configurations/image_tiff_tescan_cfg.py
pynxtools_em/configurations/image_tiff_tfs_cfg.py
pynxtools_em/configurations/image_tiff_zeiss_cfg.py
pynxtools_em/configurations/nion_cfg.py
pynxtools_em/configurations/oasis_eln_cfg.py
pynxtools_em/configurations/oasis_eln_config_cfg.py
pynxtools_em/configurations/rsciio_gatan_cfg.py
pynxtools_em/configurations/rsciio_velox_cfg.py
pynxtools_em/examples/custom_reference_frame.py
pynxtools_em/examples/diffraction_pattern_set.py
pynxtools_em/examples/ebsd_database.py
pynxtools_em/examples/ebsd_database_eln.py
pynxtools_em/examples/ebsd_database_eln_cfg.py
pynxtools_em/examples/ger_berlin_koch_cfg.py
pynxtools_em/examples/ger_berlin_koch_eln.py
pynxtools_em/geometries/euler_angle_convention.py
pynxtools_em/geometries/handed_cartesian.py
pynxtools_em/geometries/msmse_convention.py
pynxtools_em/methods/ebsd.py
pynxtools_em/methods/microstructure.py
pynxtools_em/nomad/entrypoints.py
pynxtools_em/nomad/examples/README.md
pynxtools_em/nomad/examples/downloads.archive.yaml
pynxtools_em/nomad/examples/em.archive.json
pynxtools_em/nomad/examples/em.oasis.specific.yaml
pynxtools_em/nomad/examples/em.schema.archive.yaml
pynxtools_em/nomad/examples/output.nxs_eln_data.yaml
pynxtools_em/parsers/hfive_apex.py
pynxtools_em/parsers/hfive_base.py
pynxtools_em/parsers/hfive_bruker.py
pynxtools_em/parsers/hfive_dreamthreed_legacy.py
pynxtools_em/parsers/hfive_ebsd.py
pynxtools_em/parsers/hfive_edax.py
pynxtools_em-0.4.2.dist-info/licenses/LICENSE
pynxtools_em-0.4.2.dist-info/METADATA
pynxtools_em-0.4.2.dist-info/WHEEL
pynxtools_em-0.4.2.dist-info/entry_points.txt
pynxtools_em-0.4.2.dist-info/top_level.txt
pynxtools_em-0.4.2.dist-info/RECORD
